pygenutils/__init__.py
pygenutils/arrays_and_lists/__init__.py
pygenutils/arrays_and_lists/conversions.py
pygenutils/arrays_and_lists/data_manipulation.py
pygenutils/arrays_and_lists/maths.py
pygenutils/arrays_and_lists/patterns.py
pygenutils/audio_and_video/__init__.py
pygenutils/audio_and_video/audio_and_video_manipulation.py
pygenutils/audio_and_video/merge_audio_and_video.py
pygenutils/audio_and_video/merge_audio_or_video.py
pygenutils/audio_and_video/trim_media.py
pygenutils/dictionaries/__init__.py
pygenutils/dictionaries/dict_handler.py
pygenutils/dictionaries/dict_operators.py
pygenutils/number_bases/__init__.py
pygenutils/number_bases/base_converters.py
pygenutils/number_bases/binary_operations.py
pygenutils/number_bases/bitwise_operators.py
pygenutils/number_bases/mathematical_utils.py
pygenutils/operative_systems/__init__.py
pygenutils/operative_systems/os_operations.py
pygenutils/sets_and_intervals/__init__.py
pygenutils/sets_and_intervals/interval_handler.py
pygenutils/sets_and_intervals/sets_handler.py
pygenutils/strings/__init__.py
pygenutils/strings/string_handler.py
pygenutils/strings/text_formatters.py
pygenutils/time_handling/__init__.py
pygenutils/time_handling/calendar_utils.py
pygenutils/time_handling/countdown.py
pygenutils/time_handling/date_and_time_maths.py
pygenutils/time_handling/date_and_time_utils.py
pygenutils/time_handling/program_snippet_exec_timers.py
pygenutils/time_handling/time_formatters.py
pygenutils/time_handling/time_utils.py
pygenutils-16.3.1.dist-info/licenses/LICENSE
pygenutils-16.3.1.dist-info/METADATA
pygenutils-16.3.1.dist-info/WHEEL
pygenutils-16.3.1.dist-info/top_level.txt
pygenutils-16.3.1.dist-info/RECORD
