Metadata-Version: 2.4
Name: pygenutils
Version: 16.3.1
Summary: A comprehensive Python utility library for general-purpose and specialised tasks
Author-email: Jon Ander Gabantxo <jagabantxo@gmail.com>
License: MIT License
Project-URL: Homepage, https://github.com/EusDancerDev/pygenutils
Project-URL: Documentation, https://github.com/EusDancerDev/pygenutils#readme
Project-URL: Repository, https://github.com/EusDancerDev/pygenutils.git
Project-URL: Bug Reports, https://github.com/EusDancerDev/pygenutils/issues
Keywords: utilities,python,general-purpose,file handling,string processing
Classifier: Development Status :: 4 - Beta
Classifier: Intended Audience :: Developers
Classifier: Programming Language :: Python :: 3
Classifier: Programming Language :: Python :: 3.10
Classifier: Programming Language :: Python :: 3.11
Classifier: Programming Language :: Python :: 3.12
Classifier: Operating System :: OS Independent
Classifier: Topic :: Software Development :: Libraries :: Python Modules
Classifier: Topic :: Utilities
Classifier: Typing :: Typed
Requires-Python: >=3.10
License-File: LICENSE
Requires-Dist: more_itertools>=10.0.0
Requires-Dist: numpy<2.0.0,>=1.21.0
Requires-Dist: pandas<2.0.0,>=1.3.0
Requires-Dist: filewise>=3.11.6
Requires-Dist: paramlib>=3.4.10
Provides-Extra: xarray
Requires-Dist: xarray>=2024.2.0; extra == "xarray"
Provides-Extra: arrow
Requires-Dist: arrow>=1.2.0; extra == "arrow"
Provides-Extra: dev
Requires-Dist: pytest>=7.0.0; extra == "dev"
Requires-Dist: pytest-cov>=4.0.0; extra == "dev"
Requires-Dist: black>=23.0.0; extra == "dev"
Requires-Dist: isort>=5.0.0; extra == "dev"
Requires-Dist: mypy>=1.0.0; extra == "dev"
Requires-Dist: flake8>=6.0.0; extra == "dev"
Dynamic: license-file
